sdh/table/__init__.py
sdh/table/apps.py
sdh/table/controller.py
sdh/table/datasource.py
sdh/table/models.py
sdh/table/paginator.py
sdh/table/shortcuts.py
sdh/table/table.py
sdh/table/widgets.py
sdh/table/management/__init__.py
sdh/table/management/commands/__init__.py
sdh/table/management/commands/sdh_update_table_columns.py
sdh/table/migrations/0001_initial.py
sdh/table/migrations/0002_tableviewprofile.py
sdh/table/migrations/0003_add_constraint.py
sdh/table/migrations/__init__.py
sdh/table/templates/sdh/table/table_body.html
sdh/table/templates/sdh/table/table_column_sort.html
sdh/table/templates/sdh/table/table_head.html
sdh/table/templates/sdh/table/widgets/boolean_widget.html
sdh/table/templatetags/__init__.py
sdh/table/templatetags/tableview.py
sdh/table/tests/__init__.py
sdh/table/tests/test_controller_filter.py
sdh_table-2.3.2.dist-info/licenses/LICENSE
sdh_table-2.3.2.dist-info/METADATA
sdh_table-2.3.2.dist-info/WHEEL
sdh_table-2.3.2.dist-info/top_level.txt
sdh_table-2.3.2.dist-info/RECORD
