Metadata-Version: 2.4
Name: sdh.table
Version: 2.3.2
Summary: Table rendering engine.
Author-email: Viacheslav Vic Bukhantsov <vic.bukhantsov@gmail.com>, Andriy Koziy <andriy@koziy.com>, Oleg Koziy <olekhelk@gmail.com>, Pavel Yablonskiy <yapple@ua2crm.com>, Borys Vorona <borysvorona@gmail.com>, "Oleksii (Alex) Koval" <alex@koval.kharkov.ua>
Maintainer-email: Viacheslav Vic Bukhantsov <vic.bukhantsov@gmail.com>
License: Copyright (c) Software Development Hub LLC.
Project-URL: Repository, https://github.com/sdh-global/sdh-table
Classifier: Development Status :: 5 - Production/Stable
Classifier: Environment :: Web Environment
Classifier: Framework :: Django
Classifier: Intended Audience :: Developers
Classifier: License :: OSI Approved :: BSD License
Classifier: Operating System :: OS Independent
Classifier: Programming Language :: Python
Classifier: Programming Language :: Python :: 3
Classifier: Programming Language :: Python :: 3.8
Classifier: Programming Language :: Python :: 3.9
Classifier: Topic :: Internet :: WWW/HTTP
Classifier: Topic :: Internet :: WWW/HTTP :: Dynamic Content
Classifier: Topic :: Software Development :: Libraries :: Python Modules
Requires-Python: >=3.8
License-File: LICENSE
Requires-Dist: Django>=3.2
Dynamic: license-file
